[
  {
    "Name": "yes",
    "Price": {
      "PriceDKK": 100.0,
      "PriceEuro": 13.333333333333334
    },
    "Weight": {
      "WeightKilo": 12.0,
      "WeightPound": 26.455471439999997
    },
    "Picture": null,
    "Tags": [
      "System.Collections.Generic.List`1[System.String]"
    ]
  },
  {
    "Name": "Yeast",
    "Price": {
      "PriceDKK": 100.0,
      "PriceEuro": 13.333333333333334
    },
    "Weight": {
      "WeightKilo": 222.0,
      "WeightPound": 489.42622164
    },
    "Picture": "no",
    "Tags": [
      "bløb"
    ]
  },
  {
    "Name": "tomms mælkechokolade",
    "Price": {
      "PriceDKK": 100000.0,
      "PriceEuro": 13333.333333333334
    },
    "Weight": {
      "WeightKilo": 3.0,
      "WeightPound": 6.613867859999999
    },
    "Picture": "RødBar.jpg",
    "Tags": [
      "System.Collections.Generic.List`1[System.String]"
    ]
  }
]